Getquantumopticslib/__init__.py
Getquantumopticslib/your_module.py
test/__init__.py
test/test_your_module.py
Getquantumoptics-0.0.1.dist-info/LICENSE
Getquantumoptics-0.0.1.dist-info/METADATA
Getquantumoptics-0.0.1.dist-info/WHEEL
Getquantumoptics-0.0.1.dist-info/top_level.txt
Getquantumoptics-0.0.1.dist-info/RECORD
